stanford/mais/account/__init__.py
stanford/mais/account/account.py
stanford/mais/account/py.typed
stanford/mais/account/service.py
stanford/mais/account/validate.py
stanford/mais/account/tests/mock.py
stanford/mais/client/__init__.py
stanford/mais/client/py.typed
stanford/mais/workgroup/__init__.py
stanford/mais/workgroup/member.py
stanford/mais/workgroup/properties.py
stanford/mais/workgroup/py.typed
stanford/mais/workgroup/workgroup.py
stanford/mais/workgroup/tests/mock.py
stanford_mais-0.55.0.dist-info/licenses/LICENSE
stanford_mais-0.55.0.dist-info/METADATA
stanford_mais-0.55.0.dist-info/WHEEL
stanford_mais-0.55.0.dist-info/top_level.txt
stanford_mais-0.55.0.dist-info/RECORD
