Metadata-Version: 2.4
Name: stanford-mais
Version: 0.55.0
Summary: Python client for Stanford MaIS APIs
Author-email: Stanford Research Computing <srcc-support@stanford.edu>
Maintainer-email: "A. Karl Kornel" <akkornel@stanford.edu>
License-Expression: GPL-3.0-only
Project-URL: Source, https://github.com/stanford-rc/mais-apis-python
Project-URL: Documentation, https://mais-apis-python.readthedocs.io
Project-URL: Changelog, https://github.com/stanford-rc/mais-apis-python/blob/main/CHANGELOG.rst
Project-URL: Issues, https://github.com/stanford-rc/mais-apis-python/issues
Classifier: Development Status :: 3 - Alpha
Classifier: Intended Audience :: Developers
Classifier: Operating System :: OS Independent
Classifier: Programming Language :: Python :: 3 :: Only
Classifier: Programming Language :: Python :: 3.11
Classifier: Programming Language :: Python :: 3.12
Classifier: Programming Language :: Python :: 3.13
Classifier: Programming Language :: Python :: 3.14
Classifier: Topic :: Office/Business
Classifier: Topic :: Software Development :: Libraries :: Python Modules
Requires-Python: <4.0,>=3.11
License-File: LICENSE
Requires-Dist: requests<3.0,>=2.28.2
Provides-Extra: docs
Requires-Dist: sphinx<9.0,>=5.0; extra == "docs"
Requires-Dist: sphinx-rtd-theme; extra == "docs"
Provides-Extra: test
Requires-Dist: coverage>=5.3; extra == "test"
Requires-Dist: mypy>=1.0.0; extra == "test"
Requires-Dist: types-requests; extra == "test"
Requires-Dist: pytest<8.5.0,>=8.4.1; extra == "test"
Requires-Dist: pytest-cov; extra == "test"
Requires-Dist: pytest-responses; extra == "test"
Requires-Dist: requests<3.0,>=2.30.0; extra == "test"
Requires-Dist: responses; extra == "test"
Requires-Dist: bandit>=1.7.0; extra == "test"
Dynamic: license-file
